task3/dual_ram.sv
module dual_ram #(
    parameter ADDRESS_WIDTH = 8,
              DATA_WIDTH = 8
)(
    input logic clk,
    input logic wr_en,
    input logic rd_en,
    input logic [ADDRESS_WIDTH-1:0] wr_addr,
    input logic [ADDRESS_WIDTH-1:0] rd_addr,
    input logic [DATA_WIDTH-1:0] din,
    output logic [DATA_WIDTH-1:0] dout
);

logic [DATA_WIDTH-1:0] ram_array [2**ADDRESS_WIDTH-1:0];

always_ff @(posedge clk) begin
    if (wr_en == 1'b1) ram_array[wr_addr] <= din;
    if (rd_en == 1'b1) dout <= ram_array [rd_addr];
end 

endmodule

task3/counter.sv
module counter #(
    parameter WIDTH = 8
)(
    input logic clk,
    input logic rst,
    input logic en,
    input logic diff,
    output logic [WIDTH-1:0] count1, 
    output logic [WIDTH-1:0] count2
);

always_ff @ (posedge clk or posedge rst) begin
    if (rst)begin
        count1 <= {WIDTH{1'b0}};
        count2 <= count1 + diff;
    end
    else begin
        count1 <= count1 + {{WIDTH-1{1'b0}}, en};
        count2 <= count1 + diff;
    end
end

endmodule

task3/sigdelay.sv
module sinegen #(
  parameter WIDTH = 8
)(
  input logic clk,
  input logic rst,
  input logic wr,
  input logic rd,
  input logic offset,
  input logic mic_signal,
  output logic [WIDTH-1:0] delayed_signal
);

  logic [WIDTH-1:0] count1;
  logic [WIDTH-1:0] count2;

counter myCounter (
  .clk (clk),
  .rst (rst),
  .en (1),
  .diff (offset),
  .count1 (count1),
  .count2 (count2)
);

dual_ram myDualRam (
  .clk (clk),
  .wr_en (wr),
  .rd_en (rd),
  .wr_addr (count2),
  .rd_addr (count1),
  .din (mic_signal),
  .dout (delayed_signal)
);

endmodule

task3/sigdelay.vcd
$version Generated by VerilatedVcd $end
$date Fri Oct 25 19:04:34 2024 $end
$timescale 1ps $end

 $scope module TOP $end
  $var wire  1 # clk $end
  $var wire  8 ) delayed_signal [7:0] $end
  $var wire  1 ( mic_signal $end
  $var wire  1 ' offset $end
  $var wire  1 & rd $end
  $var wire  1 $ rst $end
  $var wire  1 % wr $end
  $scope module sinegen $end
   $var wire 32 - WIDTH [31:0] $end
   $var wire  1 # clk $end
   $var wire  8 * count1 [7:0] $end
   $var wire  8 + count2 [7:0] $end
   $var wire  8 ) delayed_signal [7:0] $end
   $var wire  1 ( mic_signal $end
   $var wire  1 ' offset $end
   $var wire  1 & rd $end
   $var wire  1 $ rst $end
   $var wire  1 % wr $end
   $scope module myCounter $end
    $var wire 32 - WIDTH [31:0] $end
    $var wire  1 # clk $end
    $var wire  8 * count1 [7:0] $end
    $var wire  8 + count2 [7:0] $end
    $var wire  1 ' diff $end
    $var wire  1 . en $end
    $var wire  1 $ rst $end
   $upscope $end
   $scope module myDualRam $end
    $var wire 32 - ADDRESS_WIDTH [31:0] $end
    $var wire 32 - DATA_WIDTH [31:0] $end
    $var wire  1 # clk $end
    $var wire  8 , din [7:0] $end
    $var wire  8 ) dout [7:0] $end
    $var wire  8 * rd_addr [7:0] $end
    $var wire  1 & rd_en $end
    $var wire  8 + wr_addr [7:0] $end
    $var wire  1 % wr_en $end
   $upscope $end
  $upscope $end
 $upscope $end
$enddefinitions $end


#0
1#
0$
1%
1&
p'
0(
b00000000 )
b00000000 *
b00000000 +
b00000000 ,
b00000000000000000000000000001000 -
1.
#1
0#
#2
1#
z(
b00000001 *
b01000000 +
b01101010 ,
#3
0#
#4
1#
b00000010 *
b01000001 +
#5
0#
#6
1#
b00000011 *
b01000010 +
#7
0#
#8
1#
b00000100 *
b01000011 +
#9
0#
#10
1#
b00000101 *
b01000100 +
#11
0#
#12
1#
b00000110 *
b01000101 +
#13
0#
#14
1#
b00000111 *
b01000110 +
#15
0#
#16
1#
b00001000 *
b01000111 +
#17
0#
#18
1#
b00001001 *
b01001000 +
#19
0#
#20
1#
b00001010 *
b01001001 +
#21
0#
#22
1#
b00001011 *
b01001010 +
#23
0#
#24
1#
{(
b00001100 *
b01001011 +
b01101011 ,
#25
0#
#26
1#
z(
b00001101 *
b01001100 +
b01101010 ,
#27
0#
#28
1#
b00001110 *
b01001101 +
#29
0#
#30
1#
b00001111 *
b01001110 +
#31
0#
#32
1#
b00010000 *
b01001111 +
#33
0#
#34
1#
b00010001 *
b01010000 +
#35
0#
#36
1#
b00010010 *
b01010001 +
#37
0#
#38
1#
b00010011 *
b01010010 +
#39
0#
#40
1#
b00010100 *
b01010011 +
#41
0#
#42
1#
b00010101 *
b01010100 +
#43
0#
#44
1#
y(
b00010110 *
b01010101 +
b01101001 ,
#45
0#
#46
1#
z(
b00010111 *
b01010110 +
b01101010 ,
#47
0#
#48
1#
b00011000 *
b01010111 +
#49
0#
#50
1#
b00011001 *
b01011000 +
#51
0#
#52
1#
b00011010 *
b01011001 +
#53
0#
#54
1#
b00011011 *
b01011010 +
#55
0#
#56
1#
b00011100 *
b01011011 +
#57
0#
#58
1#
b00011101 *
b01011100 +
#59
0#
#60
1#
b00011110 *
b01011101 +
#61
0#
#62
1#
b00011111 *
b01011110 +
#63
0#
#64
1#
b00100000 *
b01011111 +
#65
0#
#66
1#
y(
b00100001 *
b01100000 +
b01101001 ,
#67
0#
#68
1#
b00100010 *
b01100001 +
#69
0#
#70
1#
b00100011 *
b01100010 +
#71
0#
#72
1#
b00100100 *
b01100011 +
#73
0#
#74
1#
z(
b00100101 *
b01100100 +
b01101010 ,
#75
0#
#76
1#
y(
b00100110 *
b01100101 +
b01101001 ,
#77
0#
#78
1#
b00100111 *
b01100110 +
#79
0#
#80
1#
b00101000 *
b01100111 +
#81
0#
#82
1#
b00101001 *
b01101000 +
#83
0#
#84
1#
z(
b00101010 *
b01101001 +
b01101010 ,
#85
0#
#86
1#
y(
b00101011 *
b01101010 +
b01101001 ,
#87
0#
#88
1#
b00101100 *
b01101011 +
#89
0#
#90
1#
b00101101 *
b01101100 +
#91
0#
#92
1#
b00101110 *
b01101101 +
#93
0#
#94
1#
b00101111 *
b01101110 +
#95
0#
#96
1#
b00110000 *
b01101111 +
#97
0#
#98
1#
b00110001 *
b01110000 +
#99
0#
#100
1#
b00110010 *
b01110001 +
#101
0#
#102
1#
b00110011 *
b01110010 +
#103
0#
#104
1#
b00110100 *
b01110011 +
#105
0#
#106
1#
b00110101 *
b01110100 +
#107
0#
#108
1#
b00110110 *
b01110101 +
#109
0#
#110
1#
b00110111 *
b01110110 +
#111
0#
#112
1#
b00111000 *
b01110111 +
#113
0#
#114
1#
b00111001 *
b01111000 +
#115
0#
#116
1#
b00111010 *
b01111001 +
#117
0#
#118
1#
b00111011 *
b01111010 +
#119
0#
#120
1#
b00111100 *
b01111011 +
#121
0#
#122
1#
b00111101 *
b01111100 +
#123
0#
#124
1#
b00111110 *
b01111101 +
#125
0#
#126
1#
b00111111 *
b01111110 +
#127
0#
#128
1#
b01000000 *
b01111111 +
#129
0#
#130
1#
b01101010 )
b01000001 *
b10000000 +
#131
0#
#132
1#
x(
b01000010 *
b10000001 +
b01101000 ,
#133
0#
#134
1#
y(
b01000011 *
b10000010 +
b01101001 ,
#135
0#
#136
1#
x(
b01000100 *
b10000011 +
b01101000 ,
#137
0#
#138
1#
y(
b01000101 *
b10000100 +
b01101001 ,
#139
0#
#140
1#
b01000110 *
b10000101 +
#141
0#
#142
1#
x(
b01000111 *
b10000110 +
b01101000 ,
#143
0#
#144
1#
y(
b01001000 *
b10000111 +
b01101001 ,
#145
0#
#146
1#
x(
b01001001 *
b10001000 +
b01101000 ,
#147
0#
#148
1#
b01001010 *
b10001001 +
#149
0#
#150
1#
b01001011 *
b10001010 +
#151
0#
#152
1#
b01101011 )
b01001100 *
b10001011 +
#153
0#
#154
1#
b01101010 )
b01001101 *
b10001100 +
#155
0#
#156
1#
y(
b01001110 *
b10001101 +
b01101001 ,
#157
0#
#158
1#
x(
b01001111 *
b10001110 +
b01101000 ,
#159
0#
#160
1#
b01010000 *
b10001111 +
#161
0#
#162
1#
b01010001 *
b10010000 +
#163
0#
#164
1#
b01010010 *
b10010001 +
#165
0#
#166
1#
b01010011 *
b10010010 +
#167
0#
#168
1#
b01010100 *
b10010011 +
#169
0#
#170
1#
b01010101 *
b10010100 +
#171
0#
#172
1#
b01101001 )
b01010110 *
b10010101 +
#173
0#
#174
1#
b01101010 )
b01010111 *
b10010110 +
#175
0#
#176
1#
b01011000 *
b10010111 +
#177
0#
#178
1#
b01011001 *
b10011000 +
#179
0#
#180
1#
w(
b01011010 *
b10011001 +
b01100111 ,
#181
0#
#182
1#
x(
b01011011 *
b10011010 +
b01101000 ,
#183
0#
#184
1#
b01011100 *
b10011011 +
#185
0#
#186
1#
w(
b01011101 *
b10011100 +
b01100111 ,
#187
0#
#188
1#
x(
b01011110 *
b10011101 +
b01101000 ,
#189
0#
#190
1#
b01011111 *
b10011110 +
#191
0#
#192
1#
b01100000 *
b10011111 +
#193
0#
#194
1#
w(
b01101001 )
b01100001 *
b10100000 +
b01100111 ,
#195
0#
#196
1#
b01100010 *
b10100001 +
#197
0#
#198
1#
b01100011 *
b10100010 +
#199
0#
#200
1#
b01100100 *
b10100011 +
#201
0#
#202
1#
b01101010 )
b01100101 *
b10100100 +
#203
0#
#204
1#
b01101001 )
b01100110 *
b10100101 +
#205
0#
#206
1#
b01100111 *
b10100110 +
#207
0#
#208
1#
b01101000 *
b10100111 +
#209
0#
#210
1#
x(
b01101001 *
b10101000 +
b01101000 ,
#211
0#
#212
1#
w(
b01101010 )
b01101010 *
b10101001 +
b01100111 ,
#213
0#
#214
1#
x(
b01101001 )
b01101011 *
b10101010 +
b01101000 ,
#215
0#
#216
1#
w(
b01101100 *
b10101011 +
b01100111 ,
#217
0#
#218
1#
b01101101 *
b10101100 +
#219
0#
#220
1#
b01101110 *
b10101101 +
#221
0#
#222
1#
b01101111 *
b10101110 +
#223
0#
#224
1#
b01110000 *
b10101111 +
#225
0#
#226
1#
b01110001 *
b10110000 +
#227
0#
#228
1#
b01110010 *
b10110001 +
#229
0#
#230
1#
b01110011 *
b10110010 +
#231
0#
#232
1#
b01110100 *
b10110011 +
#233
0#
#234
1#
b01110101 *
b10110100 +
#235
0#
#236
1#
b01110110 *
b10110101 +
#237
0#
#238
1#
b01110111 *
b10110110 +
#239
0#
#240
1#
x(
b01111000 *
b10110111 +
b01101000 ,
#241
0#
#242
1#
b01111001 *
b10111000 +
#243
0#
#244
1#
b01111010 *
b10111001 +
#245
0#
#246
1#
w(
b01111011 *
b10111010 +
b01100111 ,
#247
0#
#248
1#
x(
b01111100 *
b10111011 +
b01101000 ,
#249
0#
#250
1#
w(
b01111101 *
b10111100 +
b01100111 ,
#251
0#
#252
1#
b01111110 *
b10111101 +
#253
0#
#254
1#
b01111111 *
b10111110 +
#255
0#
#256
1#
b10000000 *
b10111111 +
#257
0#
#258
1#
b10000001 *
b11000000 +
#259
0#
#260
1#
b01101000 )
b10000010 *
b11000001 +
#261
0#
#262
1#
v(
b01101001 )
b10000011 *
b11000010 +
b01100110 ,
#263
0#
#264
1#
w(
b01101000 )
b10000100 *
b11000011 +
b01100111 ,
#265
0#
#266
1#
b01101001 )
b10000101 *
b11000100 +
#267
0#
#268
1#
b10000110 *
b11000101 +
#269
0#
#270
1#
b01101000 )
b10000111 *
b11000110 +
#271
0#
#272
1#
b01101001 )
b10001000 *
b11000111 +
#273
0#
#274
1#
b01101000 )
b10001001 *
b11001000 +
#275
0#
#276
1#
b10001010 *
b11001001 +
#277
0#
#278
1#
b10001011 *
b11001010 +
#279
0#
#280
1#
b10001100 *
b11001011 +
#281
0#
#282
1#
b10001101 *
b11001100 +
#283
0#
#284
1#
b01101001 )
b10001110 *
b11001101 +
#285
0#
#286
1#
b01101000 )
b10001111 *
b11001110 +
#287
0#
#288
1#
b10010000 *
b11001111 +
#289
0#
#290
1#
b10010001 *
b11010000 +
#291
0#
#292
1#
v(
b10010010 *
b11010001 +
b01100110 ,
#293
0#
#294
1#
w(
b10010011 *
b11010010 +
b01100111 ,
#295
0#
#296
1#
b10010100 *
b11010011 +
#297
0#
#298
1#
b10010101 *
b11010100 +
#299
0#
#300
1#
b10010110 *
b11010101 +
#301
0#
#302
1#
b10010111 *
b11010110 +
#303
0#
#304
1#
b10011000 *
b11010111 +
#305
0#
#306
1#
b10011001 *
b11011000 +
#307
0#
#308
1#
b01100111 )
b10011010 *
b11011001 +
#309
0#
#310
1#
b01101000 )
b10011011 *
b11011010 +
#311
0#
#312
1#
b10011100 *
b11011011 +
#313
0#
#314
1#
b01100111 )
b10011101 *
b11011100 +
#315
0#
#316
1#
b01101000 )
b10011110 *
b11011101 +
#317
0#
#318
1#
b10011111 *
b11011110 +
#319
0#
#320
1#
b10100000 *
b11011111 +
#321
0#
#322
1#
v(
b01100111 )
b10100001 *
b11100000 +
b01100110 ,
#323
0#
#324
1#
w(
b10100010 *
b11100001 +
b01100111 ,
#325
0#
#326
1#
b10100011 *
b11100010 +
#327
0#
#328
1#
b10100100 *
b11100011 +
#329
0#
#330
1#
v(
b10100101 *
b11100100 +
b01100110 ,
#331
0#
#332
1#
b10100110 *
b11100101 +
#333
0#
#334
1#
b10100111 *
b11100110 +
#335
0#
#336
1#
b10101000 *
b11100111 +
#337
0#
#338
1#
b01101000 )
b10101001 *
b11101000 +
#339
0#
#340
1#
w(
b01100111 )
b10101010 *
b11101001 +
b01100111 ,
#341
0#
#342
1#
b01101000 )
b10101011 *
b11101010 +
#343
0#
#344
1#
b01100111 )
b10101100 *
b11101011 +
#345
0#
#346
1#
b10101101 *
b11101100 +
#347
0#
#348
1#
b10101110 *
b11101101 +
#349
0#
#350
1#
b10101111 *
b11101110 +
#351
0#
#352
1#
v(
b10110000 *
b11101111 +
b01100110 ,
#353
0#
#354
1#
w(
b10110001 *
b11110000 +
b01100111 ,
#355
0#
#356
1#
v(
b10110010 *
b11110001 +
b01100110 ,
#357
0#
#358
1#
b10110011 *
b11110010 +
#359
0#
#360
1#
b10110100 *
b11110011 +
#361
0#
#362
1#
w(
b10110101 *
b11110100 +
b01100111 ,
#363
0#
#364
1#
b10110110 *
b11110101 +
#365
0#
#366
1#
v(
b10110111 *
b11110110 +
b01100110 ,
#367
0#
#368
1#
w(
b01101000 )
b10111000 *
b11110111 +
b01100111 ,
#369
0#
#370
1#
v(
b10111001 *
b11111000 +
b01100110 ,
#371
0#
#372
1#
w(
b10111010 *
b11111001 +
b01100111 ,
#373
0#
#374
1#
b01100111 )
b10111011 *
b11111010 +
#375
0#
#376
1#
b01101000 )
b10111100 *
b11111011 +
#377
0#
#378
1#
v(
b01100111 )
b10111101 *
b11111100 +
b01100110 ,
#379
0#
#380
1#
w(
b10111110 *
b11111101 +
b01100111 ,
#381
0#
#382
1#
b10111111 *
b11111110 +
#383
0#
#384
1#
v(
b11000000 *
b11111111 +
b01100110 ,
#385
0#
#386
1#
q'
b11000001 *
b00000000 +
#387
0#
#388
1#
b11000010 *
b00000010 +
#389
0#
#390
1#
r'
b01100110 )
b11000011 *
b00000011 +
#391
0#
#392
1#
s'
b01100111 )
b11000100 *
b00000101 +
#393
0#
#394
1#
w(
b11000101 *
b00000111 +
b01100111 ,
#395
0#
#396
1#
t'
v(
b11000110 *
b00001000 +
b01100110 ,
#397
0#
#398
1#
u'
b11000111 *
b00001010 +
#399
0#
#400
1#
v'
b11001000 *
b00001100 +
#401
0#
#402
1#
w'
w(
b11001001 *
b00001110 +
b01100111 ,
#403
0#
#404
1#
x'
b11001010 *
b00010000 +
#405
0#
#406
1#
y'
v(
b11001011 *
b00010010 +
b01100110 ,
#407
0#
#408
1#
w(
b11001100 *
b00010100 +
b01100111 ,
#409
0#
#410
1#
v(
b11001101 *
b00010101 +
b01100110 ,
#411
0#
#412
1#
b11001110 *
b00010110 +
#413
0#
#414
1#
b11001111 *
b00010111 +
#415
0#
#416
1#
b11010000 *
b00011000 +
#417
0#
#418
1#
u(
b11010001 *
b00011001 +
b01100101 ,
#419
0#
#420
1#
v(
b01100110 )
b11010010 *
b00011010 +
b01100110 ,
#421
0#
#422
1#
b01100111 )
b11010011 *
b00011011 +
#423
0#
#424
1#
b11010100 *
b00011100 +
#425
0#
#426
1#
b11010101 *
b00011101 +
#427
0#
#428
1#
b11010110 *
b00011110 +
#429
0#
#430
1#
b11010111 *
b00011111 +
#431
0#
#432
1#
b11011000 *
b00100000 +
#433
0#
#434
1#
x'
w(
b11011001 *
b00100001 +
b01100111 ,
#435
0#
#436
1#
w'
v(
b11011010 *
b01100110 ,
#437
0#
#438
1#
s'
w(
b11011011 *
b01100111 ,
#439
0#
#440
1#
q'
v(
b11011100 *
b00011110 +
b01100110 ,
#441
0#
#442
1#
p'
b11011101 *
b00011101 +
#443
0#
#444
1#
?'
b11011110 *
#445
0#
#446
1#
b11011111 *
#447
0#
#448
1#
b11100000 *
b00011110 +
#449
0#
#450
1#
b01100110 )
b11100001 *
b00011111 +
#451
0#
#452
1#
b01100111 )
b11100010 *
b00100000 +
#453
0#
#454
1#
b11100011 *
b00100001 +
#455
0#
#456
1#
w(
b11100100 *
b00100010 +
b01100111 ,
#457
0#
#458
1#
v(
b01100110 )
b11100101 *
b00100011 +
b01100110 ,
#459
0#
#460
1#
b11100110 *
b00100100 +
#461
0#
#462
1#
<'
b11100111 *
b00100101 +
#463
0#
#464
1#
:'
b11101000 *
b00100011 +
#465
0#
#466
1#
8'
w(
b11101001 *
b00100010 +
b01100111 ,
#467
0#
#468
1#
7'
b01100111 )
b11101010 *
b00100001 +
#469
0#
#470
1#
v(
b11101011 *
b01100110 ,
#471
0#
#472
1#
w(
b11101100 *
b00100010 +
b01100111 ,
#473
0#
#474
1#
v(
b11101101 *
b00100011 +
b01100110 ,
#475
0#
#476
1#
b11101110 *
b00100100 +
#477
0#
#478
1#
b11101111 *
b00100101 +
#479
0#
#480
1#
b01100110 )
b11110000 *
b00100110 +
#481
0#
#482
1#
5'
b01100111 )
b11110001 *
b00100111 +
#483
0#
#484
1#
2'
b01100110 )
b11110010 *
b00100110 +
#485
0#
#486
1#
?'
b11110011 *
b00100100 +
#487
0#
#488
1#
b11110100 *
b00100010 +
#489
0#
#490
1#
b01100111 )
b11110101 *
b00100011 +
#491
0#
#492
1#
b11110110 *
b00100100 +
#493
0#
#494
1#
b01100110 )
b11110111 *
b00100101 +
#495
0#
#496
1#
b01100111 )
b11111000 *
b00100110 +
#497
0#
#498
1#
b01100110 )
b11111001 *
b00100111 +
#499
0#
#500
1#
w(
b01100111 )
b11111010 *
b00101000 +
b01100111 ,
#501
0#
#502
1#
;'
v(
b11111011 *
b00101001 +
b01100110 ,
#503
0#
#504
1#
8'
w(
b11111100 *
b00100110 +
b01100111 ,
#505
0#
#506
1#
7'
b01100110 )
b11111101 *
b00100100 +
#507
0#
#508
1#
v(
b01100111 )
b11111110 *
b01100110 ,
#509
0#
#510
1#
b11111111 *
b00100101 +
#511
0#
#512
1#
b01100110 )
b00000000 *
b00100110 +
#513
0#
#514
1#
z(
b00000001 *
b00100111 +
b01101010 ,
#515
0#
#516
1#
q(
b00000000 )
b00000010 *
b00101000 +
b01110001 ,
#517
0#
#518
1#
t(
b01100110 )
b00000011 *
b00101001 +
b01110100 ,
#519
0#
#520
1#
6'
w(
b00000100 *
b00101010 +
b01110111 ,
#521
0#
#522
1#
3'
z(
b00000000 )
b00000101 *
b01111010 ,
#523
0#
#524
1#
1'
v(
b01100110 )
b00000110 *
b00101000 +
b01110110 ,
#525
0#
#526
1#
0'
t(
b00000000 )
b00000111 *
b00100111 +
b01110100 ,
#527
0#
#528
1#
p(
b01100111 )
b00001000 *
b01110000 ,
#529
0#
#530
1#
r(
b01100110 )
b00001001 *
b00101000 +
b01110010 ,
#531
0#
#532
1#
~(
b00000000 )
b00001010 *
b00101001 +
b01101110 ,
#533
0#
#534
1#
|(
b01100110 )
b00001011 *
b00101010 +
b01101100 ,
#535
0#
#536
1#
(
b00000000 )
b00001100 *
b00101011 +
b01011111 ,
#537
0#
#538
1#
r(
b01100110 )
b00001101 *
b00101100 +
b01100010 ,
#539
0#
#540
1#
p(
b00000000 )
b00001110 *
b00101101 +
b01100000 ,
#541
0#
#542
1#
w(
b01100111 )
b00001111 *
b00101110 +
b01010111 ,
#543
0#
#544
1#
t(
b00000000 )
b00010000 *
b00101111 +
b01100100 ,
#545
0#
#546
1#
w(
b01100111 )
b00010001 *
b00110000 +
b01100111 ,
#547
0#
#548
1#
(
b00000000 )
b00010010 *
b00110001 +
b01011111 ,
#549
0#
#550
1#
|(
b01100110 )
b00010011 *
b00110010 +
b01101100 ,
#551
0#
#552
1#
s(
b00000000 )
b00010100 *
b00110011 +
b01100011 ,
#553
0#
#554
1#
q(
b01100111 )
b00010101 *
b00110100 +
b01110001 ,
#555
0#
#556
1#
?'
(
b01100110 )
b00010110 *
b00110101 +
b01101111 ,
#557
0#
#558
1#
>'
q(
b00010111 *
b01110001 ,
#559
0#
#560
1#
<'
v(
b00011000 *
b01110110 ,
#561
0#
#562
1#
;'
p(
b00011001 *
b00110100 +
b01110000 ,
#563
0#
#564
1#
:'
s(
b01100101 )
b00011010 *
b01110011 ,
#565
0#
#566
1#
p(
b01100110 )
b00011011 *
b01110000 ,
#567
0#
#568
1#
{(
b00011100 *
b00110101 +
b01101011 ,
#569
0#
#570
1#
(
b00011101 *
b00110110 +
b01101111 ,
#571
0#
#572
1#
z(
b00011110 *
b00110111 +
b01101010 ,
#573
0#
#574
1#
w(
b00011111 *
b00111000 +
b01100111 ,
#575
0#
#576
1#
s(
b00100000 *
b00111001 +
b01100011 ,
#577
0#
#578
1#
v(
b00100001 *
b00111010 +
b01100110 ,
#579
0#
#580
1#
x(
b00100010 *
b00111011 +
b01101000 ,
#581
0#
#582
1#
(
b00100011 *
b00111100 +
b01011111 ,
#583
0#
#584
1#
q(
b00100100 *
b00111101 +
b01100001 ,
#585
0#
#586
1#
9'
u(
b00100101 *
b00111110 +
b01100101 ,
#587
0#
#588
1#
8'
b00100110 *
#589
0#
#590
1#
5'
~(
b00100111 *
b01101110 ,
#591
0#
#592
1#
4'
|(
b01110000 )
b00101000 *
b00111100 +
b01101100 ,
#593
0#
#594
1#
(
b01110010 )
b00101001 *
b01101111 ,
#595
0#
#596
1#
u(
b01101110 )
b00101010 *
b00111101 +
b01110101 ,
#597
0#
#598
1#
(
b01101100 )
b00101011 *
b00111110 +
b01101111 ,
#599
0#
#600
1#
b01011111 )
b00101100 *
b00111111 +
#601
0#
#602
1#
q(
b01100010 )
b00101101 *
b01000000 +
b01110001 ,
#603
0#
#604
1#
~(
b01100000 )
b00101110 *
b01000001 +
b01101110 ,
#605
0#
#606
1#
x(
b01010111 )
b00101111 *
b01000010 +
b01101000 ,
#607
0#
#608
1#
y(
b01100100 )
b00110000 *
b01000011 +
b01101001 ,
#609
0#
#610
1#
s(
b01100111 )
b00110001 *
b01000100 +
b01100011 ,
#611
0#
#612
1#
y(
b01011111 )
b00110010 *
b01000101 +
b01101001 ,
#613
0#
#614
1#
3'
p(
b01101100 )
b00110011 *
b01000110 +
b01100000 ,
#615
0#
#616
1#
1'
b01100011 )
b00110100 *
#617
0#
#618
1#
0'
v(
b01110000 )
b00110101 *
b01000101 +
b01100110 ,
#619
0#
#620
1#
?'
t(
b01101011 )
b00110110 *
b01100100 ,
#621
0#
#622
1#
>'
y(
b01101111 )
b00110111 *
b01101001 ,
#623
0#
#624
1#
x(
b01101010 )
b00111000 *
b01101000 ,
#625
0#
#626
1#
z(
b01100111 )
b00111001 *
b01000110 +
b01101010 ,
#627
0#
#628
1#
b01100011 )
b00111010 *
b01000111 +
#629
0#
#630
1#
{(
b01100110 )
b00111011 *
b01001000 +
b01101011 ,
#631
0#
#632
1#
|(
b01101000 )
b00111100 *
b01001001 +
b01101100 ,
#633
0#
#634
1#
w(
b01101111 )
b00111101 *
b01001010 +
b01100111 ,
#635
0#
#636
1#
y(
b01110101 )
b00111110 *
b01001011 +
b01101001 ,
#637
0#
#638
1#
u(
b01101111 )
b00111111 *
b01001100 +
b01100101 ,
#639
0#
#640
1#
='
s(
b01000000 *
b01001101 +
b01100011 ,
#641
0#
#642
1#
<'
y(
b01110001 )
b01000001 *
b01101001 ,
#643
0#
#644
1#
;'
x(
b01101110 )
b01000010 *
b01101000 ,
#645
0#
#646
1#
v(
b01101000 )
b01000011 *
b01100110 ,
#647
0#
#648
1#
:'
t(
b01101001 )
b01000100 *
b01001110 +
b01100100 ,
#649
0#
#650
1#
b01100011 )
b01000101 *
#651
0#
#652
1#
u(
b01101000 )
b01000110 *
b01001111 +
b01100101 ,
#653
0#
#654
1#
v(
b01101010 )
b01000111 *
b01010000 +
b01100110 ,
#655
0#
#656
1#
u(
b01001000 *
b01010001 +
b01100101 ,
#657
0#
#658
1#
y(
b01101011 )
b01001001 *
b01010010 +
b01101001 ,
#659
0#
#660
1#
b01101100 )
b01001010 *
b01010011 +
#661
0#
#662
1#
u(
b01100111 )
b01001011 *
b01010100 +
b01100101 ,
#663
0#
#664
1#
y(
b01101001 )
b01001100 *
b01010101 +
b01101001 ,
#665
0#
#666
1#
z(
b01100101 )
b01001101 *
b01010110 +
b01101010 ,
#667
0#
#668
1#
}(
b01100110 )
b01001110 *
b01010111 +
b01101101 ,
#669
0#
#670
1#
{(
b01100100 )
b01001111 *
b01011000 +
b01101011 ,
#671
0#
#672
1#
y(
b01100101 )
b01010000 *
b01011001 +
b01101001 ,
#673
0#
#674
1#
{(
b01100110 )
b01010001 *
b01011010 +
b01101011 ,
#675
0#
#676
1#
b01100101 )
b01010010 *
b01011011 +
#677
0#
#678
1#
z(
b01101001 )
b01010011 *
b01011100 +
b01101010 ,
#679
0#
#680
1#
b01010100 *
b01011101 +
#681
0#
#682
1#
w(
b01100101 )
b01010101 *
b01011110 +
b01100111 ,
#683
0#
#684
1#
r(
b01101001 )
b01010110 *
b01011111 +
b01100010 ,
#685
0#
#686
1#
t(
b01101010 )
b01010111 *
b01100000 +
b01100100 ,
#687
0#
#688
1#
r(
b01101101 )
b01011000 *
b01100001 +
b01100010 ,
#689
0#
#690
1#
t(
b01101011 )
b01011001 *
b01100010 +
b01100100 ,
#691
0#
#692
1#
u(
b01101001 )
b01011010 *
b01100011 +
b01100101 ,
#693
0#
#694
1#
s(
b01101011 )
b01011011 *
b01100100 +
b01100011 ,
#695
0#
#696
1#
w(
b01011100 *
b01100101 +
b01100111 ,
#697
0#
#698
1#
t(
b01101010 )
b01011101 *
b01100110 +
b01100100 ,
#699
0#
#700
1#
v(
b01011110 *
b01100111 +
b01100110 ,
#701
0#
#702
1#
y(
b01100111 )
b01011111 *
b01101000 +
b01101001 ,
#703
0#
#704
1#
z(
b01100010 )
b01100000 *
b01101001 +
b01101010 ,
#705
0#
#706
1#
y(
b01100100 )
b01100001 *
b01101010 +
b01101001 ,
#707
0#
#708
1#
|(
b01100010 )
b01100010 *
b01101011 +
b01101100 ,
#709
0#
#710
1#
b01100100 )
b01100011 *
b01101100 +
#711
0#
#712
1#
}(
b01100101 )
b01100100 *
b01101101 +
b01101101 ,
#713
0#
#714
1#
|(
b01100011 )
b01100101 *
b01101110 +
b01101100 ,
#715
0#
#716
1#
{(
b01100111 )
b01100110 *
b01101111 +
b01101011 ,
#717
0#
#718
1#
x(
b01100100 )
b01100111 *
b01110000 +
b01101000 ,
#719
0#
#720
1#
{(
b01100110 )
b01101000 *
b01110001 +
b01101011 ,
#721
0#
#722
1#
u(
b01101001 )
b01101001 *
b01110010 +
b01100101 ,
#723
0#
#724
1#
{(
b01101010 )
b01101010 *
b01110011 +
b01101011 ,
#725
0#
#726
1#
u(
b01101001 )
b01101011 *
b01110100 +
b01100101 ,
#727
0#
#728
1#
v(
b01101100 )
b01101100 *
b01110101 +
b01100110 ,
#729
0#
#730
1#
x(
b01101101 *
b01110110 +
b01101000 ,
#731
0#
#732
1#
v(
b01101101 )
b01101110 *
b01110111 +
b01100110 ,
#733
0#
#734
1#
b01101100 )
b01101111 *
b01111000 +
#735
0#
#736
1#
z(
b01101011 )
b01110000 *
b01111001 +
b01101010 ,
#737
0#
#738
1#
x(
b01101000 )
b01110001 *
b01111010 +
b01101000 ,
#739
0#
#740
1#
b01101011 )
b01110010 *
b01111011 +
#741
0#
#742
1#
y(
b01100101 )
b01110011 *
b01111100 +
b01101001 ,
#743
0#
#744
1#
{(
b01101011 )
b01110100 *
b01111101 +
b01101011 ,
#745
0#
#746
1#
y(
b01100101 )
b01110101 *
b01111110 +
b01101001 ,
#747
0#
#748
1#
|(
b01100110 )
b01110110 *
b01111111 +
b01101100 ,
#749
0#
#750
1#
}(
b01101000 )
b01110111 *
b10000000 +
b01101101 ,
#751
0#
#752
1#
y(
b01100110 )
b01111000 *
b10000001 +
b01101001 ,
#753
0#
#754
1#
x(
b01111001 *
b10000010 +
b01101000 ,
#755
0#
#756
1#
z(
b01101010 )
b01111010 *
b10000011 +
b01101010 ,
#757
0#
#758
1#
x(
b01101000 )
b01111011 *
b10000100 +
b01101000 ,
#759
0#
#760
1#
z(
b01111100 *
b10000101 +
b01101010 ,
#761
0#
#762
1#
v(
b01101001 )
b01111101 *
b10000110 +
b01100110 ,
#763
0#
#764
1#
z(
b01101011 )
b01111110 *
b10000111 +
b01101010 ,
#765
0#
#766
1#
w(
b01101001 )
b01111111 *
b10001000 +
b01100111 ,
#767
0#
#768
1#
x(
b01101100 )
b10000000 *
b10001001 +
b01101000 ,
#769
0#
#770
1#
y(
b01101101 )
b10000001 *
b10001010 +
b01101001 ,
#771
0#
#772
1#
w(
b01101001 )
b10000010 *
b10001011 +
b01100111 ,
#773
0#
#774
1#
y(
b01101000 )
b10000011 *
b10001100 +
b01101001 ,
#775
0#
#776
1#
w(
b01101010 )
b10000100 *
b10001101 +
b01100111 ,
#777
0#
